ensemble_outlier_sample_detection/__init__.py
ensemble_outlier_sample_detection/ensemble_outlier_sample_detection.py
ensemble_outlier_sample_detection-0.1.0.dist-info/LICENSE
ensemble_outlier_sample_detection-0.1.0.dist-info/METADATA
ensemble_outlier_sample_detection-0.1.0.dist-info/WHEEL
ensemble_outlier_sample_detection-0.1.0.dist-info/top_level.txt
ensemble_outlier_sample_detection-0.1.0.dist-info/RECORD
