Metadata-Version: 2.1
Name: ensemble-outlier-sample-detection
Version: 0.1.0
Summary: You can do outlier detection.
Home-page: https://github.com/yu-9824/ensemble_outlier_sample_detection/
Author: yu9824
Author-email: yu.9824.job@gmail.com
Maintainer: yu9824
Maintainer-email: yu.9824.job@gmail.com
License: Apache License 2.0
Platform: UNKNOWN
Classifier: License :: OSI Approved :: Apache Software License
Classifier: Programming Language :: Python :: 3
Classifier: Programming Language :: Python :: 3.6
Classifier: Programming Language :: Python :: 3.7
Classifier: Programming Language :: Python :: 3.8
Classifier: Programming Language :: Python :: 3.9
Requires-Dist: optuna (>=0.19.0)
Requires-Dist: numpy
Requires-Dist: pandas
Requires-Dist: scikit-learn
Requires-Dist: tqdm
